quinn/__init__.py
quinn/ens/__init__.py
quinn/ens/learner.py
quinn/func/__init__.py
quinn/func/funcs.py
quinn/mcmc/__init__.py
quinn/mcmc/admcmc.py
quinn/mcmc/hmc.py
quinn/mcmc/mala.py
quinn/mcmc/mcmc.py
quinn/nns/__init__.py
quinn/nns/losses.py
quinn/nns/mlp.py
quinn/nns/nnbase.py
quinn/nns/nnfit.py
quinn/nns/nns.py
quinn/nns/nnwrap.py
quinn/nns/rnet.py
quinn/nns/tchutils.py
quinn/rvar/__init__.py
quinn/rvar/rvs.py
quinn/solvers/__init__.py
quinn/solvers/nn_ens.py
quinn/solvers/nn_laplace.py
quinn/solvers/nn_mcmc.py
quinn/solvers/nn_rms.py
quinn/solvers/nn_swag.py
quinn/solvers/nn_vi.py
quinn/solvers/quinn.py
quinn/utils/__init__.py
quinn/utils/maps.py
quinn/utils/plotting.py
quinn/utils/stats.py
quinn/utils/xutils.py
quinn/vi/__init__.py
quinn/vi/bnet.py
uqinn-1.0.0.dist-info/licenses/LICENSE
uqinn-1.0.0.dist-info/METADATA
uqinn-1.0.0.dist-info/WHEEL
uqinn-1.0.0.dist-info/top_level.txt
uqinn-1.0.0.dist-info/RECORD
